ezmsg/py.typed
ezmsg/event/__init__.py
ezmsg/event/__version__.py
ezmsg/event/binned.py
ezmsg/event/kernel.py
ezmsg/event/kernel_activation.py
ezmsg/event/kernel_insert.py
ezmsg/event/message.py
ezmsg/event/peak.py
ezmsg/event/poissonevents.py
ezmsg/event/rate.py
ezmsg/event/refractory.py
ezmsg/event/util/__init__.py
ezmsg/event/util/array.py
ezmsg/event/util/simulate.py
ezmsg_event-0.6.0.dist-info/METADATA
ezmsg_event-0.6.0.dist-info/WHEEL
ezmsg_event-0.6.0.dist-info/licenses/LICENSE
ezmsg_event-0.6.0.dist-info/RECORD
