Metadata-Version: 2.4
Name: ezmsg-event
Version: 0.6.0
Summary: Namespace package for ezmsg to work with signal events like neural spikes and heartbeats
Author-email: Chadwick Boulay <chadwick.boulay@gmail.com>
License-File: LICENSE
Requires-Python: >=3.10.15
Requires-Dist: ezmsg-baseproc>=1.1.0
Requires-Dist: ezmsg-sigproc>=2.4.0
Requires-Dist: ezmsg>=3.6.1
Requires-Dist: numpy>=2.2.6
Requires-Dist: sparse>=0.17.0
